<?xml version="1.0" encoding="utf-8" ?>
<dwsync>
<file name="demo_table.css" server="justzhl.j1.fjjsp.net//webapps/ROOT/" local="130119697420000000" remote="130123917000000000" />
<file name="jquery-1.9.1.min.js" server="justzhl.j1.fjjsp.net//webapps/ROOT/" local="130115519320000000" remote="130123917000000000" />
<file name="jquery.dataTables.min.js" server="justzhl.j1.fjjsp.net//webapps/ROOT/" local="129928516300000000" remote="130123917000000000" />
<file name="jquery-ui-1.7.2.custom.css" server="justzhl.j1.fjjsp.net//webapps/ROOT/" local="130120189380000000" remote="130123917000000000" />
<file name="demo_table_jui.css" server="justzhl.j1.fjjsp.net//webapps/ROOT/" local="130120195800000000" remote="130123917000000000" />
<file name="index.html" server="justzhl.j1.fjjsp.net//webapps/ROOT/" local="130120196620000000" remote="130123917000000000" />
<file name="demo_page.css" server="justzhl.j1.fjjsp.net//webapps/ROOT/" local="130122944100000000" remote="130123917000000000" />
<file name="listpickedcourses.html" server="justzhl.j1.fjjsp.net//webapps/ROOT/" local="130123150020000000" remote="130123917000000000" />
</dwsync>